crackpass/__init__.py
crackpass/__main__.py
crackpass/wordlists/indian-passwords-length8-20.txt
crackpass/wordlists/indian-passwords.txt
crackpass/wordlists/rockyou_aa
crackpass/wordlists/rockyou_ab
crackpass/wordlists/rockyou_ac
crackpass-1.0.0.dist-info/licenses/LICENSE
crackpass-1.0.0.dist-info/METADATA
crackpass-1.0.0.dist-info/WHEEL
crackpass-1.0.0.dist-info/entry_points.txt
crackpass-1.0.0.dist-info/top_level.txt
crackpass-1.0.0.dist-info/RECORD
