Metadata-Version: 2.4
Name: crackpass
Version: 1.0.0
Summary: A password strength analyzer using real-world cracking techniques.
Home-page: https://github.com/cracking-bytes/Crack-Pass
Author: Bhavika Nagdeo
Author-email: bhavikanagdeo83@gmail.com
Project-URL: Bug Tracker, https://github.com/cracking-bytes/Crack-Pass/issues
Classifier: Programming Language :: Python :: 3
Classifier: License :: OSI Approved :: MIT License
Classifier: Operating System :: OS Independent
Requires-Python: >=3.6
License-File: LICENSE
Dynamic: author
Dynamic: author-email
Dynamic: classifier
Dynamic: description
Dynamic: description-content-type
Dynamic: home-page
Dynamic: license-file
Dynamic: project-url
Dynamic: requires-python
Dynamic: summary
